http_misc/__init__.py
http_misc/cache.py
http_misc/errors.py
http_misc/http_utils.py
http_misc/logger.py
http_misc/retry_policy.py
http_misc/services.py
http_misc/transformers.py
http_misc-1.0.4.dist-info/METADATA
http_misc-1.0.4.dist-info/WHEEL
http_misc-1.0.4.dist-info/top_level.txt
http_misc-1.0.4.dist-info/RECORD
