Metadata-Version: 2.4
Name: http-misc
Version: 1.0.4
Summary: Утилитарный пакет межсервисного взаимодействия по протоколу HTTP
Author: Anton Gorinenko
Author-email: anton.gorinenko@gmail.com
Keywords: python,utils,http
Classifier: Programming Language :: Python :: 3.10
Classifier: Programming Language :: Python :: 3.11
Classifier: Programming Language :: Python :: 3.12
Classifier: Programming Language :: Python :: 3.13
Classifier: Operating System :: OS Independent
Requires-Python: >=3.10
Requires-Dist: aiohttp
Provides-Extra: test
Requires-Dist: pytest; extra == "test"
Requires-Dist: python-dotenv; extra == "test"
Requires-Dist: envparse; extra == "test"
Requires-Dist: pytest-asyncio; extra == "test"
Requires-Dist: pytest-mock; extra == "test"
Requires-Dist: pytest-env; extra == "test"
Requires-Dist: freezegun; extra == "test"
Dynamic: author
Dynamic: author-email
Dynamic: classifier
Dynamic: description-content-type
Dynamic: keywords
Dynamic: provides-extra
Dynamic: requires-dist
Dynamic: requires-python
Dynamic: summary
